LICENSE
MANIFEST.in
README
setup.py
Flask_Testing.egg-info/PKG-INFO
Flask_Testing.egg-info/SOURCES.txt
Flask_Testing.egg-info/dependency_links.txt
Flask_Testing.egg-info/not-zip-safe
Flask_Testing.egg-info/requires.txt
Flask_Testing.egg-info/top_level.txt
docs/Makefile
docs/conf.py
docs/index.rst
docs/make.bat
docs/_static/flask-testing.png
docs/_themes/README
docs/_themes/flask_theme_support.py
docs/_themes/flask/theme.conf
docs/_themes/flask/static/flasky.css_t
docs/_themes/flask_small/layout.html
docs/_themes/flask_small/theme.conf
docs/_themes/flask_small/static/flasky.css_t
flask_testing/__init__.py
flask_testing/twill.py
flask_testing/utils.py
tests/__init__.py
tests/__main__.py
tests/run.py
tests/test_twill.py
tests/test_utils.py
tests/flask_app/__init__.py
tests/flask_app/templates/index.html